thai_identity_generator/__init__.py
thai_identity_generator/core.py
thai_identity_generator-0.1.0.dist-info/METADATA
thai_identity_generator-0.1.0.dist-info/WHEEL
thai_identity_generator-0.1.0.dist-info/RECORD
