Metadata-Version: 2.3
Name: thai-identity-generator
Version: 0.1.0
Summary: Generate Thai National Identity Numbers programmatically for testing
Author: mohammed.saleel0099@gmail.com
Requires-Python: >=3.8,<4.0
Classifier: Programming Language :: Python :: 3
Classifier: Programming Language :: Python :: 3.8
Classifier: Programming Language :: Python :: 3.9
Classifier: Programming Language :: Python :: 3.10
Classifier: Programming Language :: Python :: 3.11
Classifier: Programming Language :: Python :: 3.12
Classifier: Programming Language :: Python :: 3.13
